pywintun_pmd3.cp313-win_amd64.pyd
wintun_driver/__init__.py
wintun_driver/__main__.py
pywintun_pmd3-0.0.4.dist-info/COPYING
pywintun_pmd3-0.0.4.dist-info/METADATA
pywintun_pmd3-0.0.4.dist-info/WHEEL
pywintun_pmd3-0.0.4.dist-info/top_level.txt
pywintun_pmd3-0.0.4.dist-info/RECORD
